Workbook

Sheet Read me
A1: JARVUS 3 - BOTS (version 5)
A2: What this is: ONLY the 99 bots that Jarvus controls (US stocks, crypto, meme coins; no ETFs). Jarvus himself is the 100th agent and lives in JARVUS_1_MASTER_PROMPT.md. The strategy library is JARVUS_2_STRATEGIES.xlsx. Dropped from the old 100: A061 META (0 test trades).
A3: Status meanings:
A4: - WATCH: the only 3 bots marked RESEARCH FURTHER. Re-test with more data. Still no trading.
A5: - RETRAIN: 1-hour bots with enough data. Retrain with the new strategy list (columns New candidate 1-3).
A6: - NEEDS DATA: 15-minute bots. US stocks only had ~2 months of data and 0-9 test trades, so their results (good or bad) mean nothing. Get 6+ months of 15m data, then retrain.
A7: - MEME SHADOW: the 15 meme-coin bots as a paper-only sleeve (max 5% of paper capital, 0.25% risk per trade). Trend candidates only. Expect them to fail the gate.
A8: - PARKED: switched off, not deleted. Crypto bots that clearly lost or had too few trades.
A9: The big organization fix (v3): test by ROLE, not by single bot.
A10: - Old way: each bot tested alone on ~12-34 trades. That can never pass the 30-trade gate and gives each bot 3 tries to get lucky.
A11: - New way: one decision per role (3 candidates), tested once on all the role's bots pooled together. About 8 roles x 3 = 24 tries instead of 60+ bots x 3.
A12: - Caution: stocks move together, so pooled trades are not fully independent. Count independent trading days, not just trades.
... A25: - Nothing is allowed to trade: still 0 of 99. Paper only.

Sheet Summary
A1: Summary
A3: Status | B3: Bots | C3: Meaning
A4: WATCH | B4: =COUNTIF(Bots!B:B,A4) -> 3 | C4: Re-test, no trading
A5: RETRAIN | B5: =COUNTIF(Bots!B:B,A5) -> 29 | C5: Retrain with new list now
A6: NEEDS DATA | B6: =COUNTIF(Bots!B:B,A6) -> 27 | C6: Wait for 6+ months of 15m data
A7: MEME SHADOW | B7: =COUNTIF(Bots!B:B,A7) -> 15 | C7: Paper-only meme sleeve (max 5%)
A8: PARKED | B8: =COUNTIF(Bots!B:B,A8) -> 25 | C8: Off, kept on file
A9: Total | B9: =SUM(B4:B8) -> 99
A10: Active roster (not parked) | B10: =B9-B8 -> 74
A11: Allowed to trade today | B11: =COUNTIF(Bots!U:U,"Yes*") -> 0

Sheet Bots
A1: Agent | B1: Status | C1: Priority | D1: Group | E1: Role | F1: Instrument | G1: Bar | H1: Old strategy | I1: Old test Sharpe | J1: Old test trades | K1: Old DSR | L1: Old PBO | M1: Old verdict | N1: New candidate 1 | O1: New candidate 2 | P1: New candidate 3 | Q1: Day trade settings | R1: Canada venue check | S1: Why | T1: Training data | U1: Allowed to trade | V1: Min stop (ATR) | W1: Weekend entries | X1: Stale if bar older than
A2: A073 | B2: WATCH | C2: 1 - first | D2: US stocks | E2: Large US stocks: mean reversion | F2: JPM | G2: 1h | H2: zscore_reversion.none.atr_bracket | I2: 2.71 | J2: 12 | K2: 0.08 | L2: 0.06 | M2: RESEARCH FURTHER | N2: ibs_reversion.trend200.time | O2: rsi2_reversion.trend200.time | P2: zscore_reversion.none.atr_bracket | Q2: Long only. Flat by 3:55 pm ET. Max 5 bars per trade (never overnight). | R2: IBKR Canada (API). Alpaca live not open to Canadians | S2: Only bots flagged RESEARCH FURTHER. Re-test with more data; still no trading. | T2: yahoo 3476 bars 2024-10-15 to 2026-10-13 | U2: No - stays in cash | V2: 2 | W2: n/a (market closed) | X2: bar size + 15 min
A3: A081 | B3: WATCH | C3: 1 - first | D3: US stocks | E3: Large US stocks: mean reversion | F3: WMT | G3: 1h | H3: zscore_reversion.none.atr_bracket | I3: 0.49 | J3: 34 | K3: 0 | L3: 0.1 | M3: RESEARCH FURTHER | N3: ibs_reversion.trend200.time | O3: rsi2_reversion.trend200.time | P3: zscore_reversion.none.atr_bracket | Q3: Long only. Flat by 3:55 pm ET. Max 5 bars per trade (never overnight). | R3: IBKR Canada (API). Alpaca live not open to Canadians | S3: Only bots flagged RESEARCH FURTHER. Re-test with more data; still no trading. | T3: yahoo 3477 bars 2024-10-15 to 2026-10-13 | U3: No - stays in cash | V3: 2 | W3: n/a (market closed) | X3: bar size + 15 min
A4: A087 | B4: WATCH | C4: 1 - first | D4: US stocks | E4: Large US stocks: mean reversion | F4: MRK | G4: 1h | H4: zscore_reversion.none.atr_bracket | I4: 2.92 | J4: 14 | K4: 0.08 | L4: 0.5 | M4: RESEARCH FURTHER | N4: ibs_reversion.trend200.time | O4: rsi2_reversion.trend200.time | P4: zscore_reversion.none.atr_bracket | Q4: Long only. Flat by 3:55 pm ET. Max 5 bars per trade (never overnight). | R4: IBKR Canada (API). Alpaca live not open to Canadians | S4: Only bots flagged RESEARCH FURTHER. Re-test with more data; still no trading. | T4: yahoo 3476 bars 2024-10-15 to 2026-10-13 | U4: No - stays in cash | V4: 2 | W4: n/a (market closed) | X4: bar size + 15 min
A5: A001 | B5: RETRAIN | C5: 1 - first | D5: Crypto | E5: Crypto majors: trend | F5: BTC-USD | G5: 1h | H5: ema_cross.adx.flip | I5: -5.28 | J5: 86 | K5: 0 | L5: 0.28 | M5: REJECT | N5: donchian_trend.adx.trail | O5: vol_breakout.adx.atr_bracket | P5: nr7_breakout.adx.atr_bracket | Q5: Long only. Max 12 bars (12 h) per trade. Max 2 crypto bots open at once. | R5: Verify the coin is on NDAX/Kraken/Coinbase Canada | S5: BTC/ETH/SOL: deepest books, keep them even though v1 lost. | T5: coinbase 19994 bars 2024-07-02 to 2026-10-14 | U5: No - stays in cash | V5: 3 | W5: No entries Sat/Sun | X5: bar size + 15 min
A6: A002 | B6: RETRAIN | C6: 1 - first | D6: Crypto | E6: Crypto majors: trend | F6: ETH-USD | G6: 1h | H6: donchian_breakout.none.trail | I6: -1.55 | J6: 48 | K6: 0.02 | M6: REJECT | N6: donchian_trend.adx.trail | O6: vol_breakout.adx.atr_bracket | P6: nr7_breakout.adx.atr_bracket | Q6: Long only. Max 12 bars (12 h) per trade. Max 2 crypto bots open at once. | R6: Verify the coin is on NDAX/Kraken/Coinbase Canada | S6: BTC/ETH/SOL: deepest books, keep them even though v1 lost. | T6: coinbase 19994 bars 2024-07-02 to 2026-10-14 | U6: No - stays in cash | V6: 3 | W6: No entries Sat/Sun | X6: bar size + 15 min
A7: A003 | B7: RETRAIN | C7: 1 - first | D7: Crypto | E7: Crypto majors: trend | F7: SOL-USD | G7: 1h | H7: tsmom.none.trail | I7: -6.35 | J7: 58 | K7: 0 | L7: 0.12 | M7: REJECT | N7: donchian_trend.adx.trail | O7: vol_breakout.adx.atr_bracket | P7: nr7_breakout.adx.atr_bracket | Q7: Long only. Max 12 bars (12 h) per trade. Max 2 crypto bots open at once. | R7: Verify the coin is on NDAX/Kraken/Coinbase Canada | S7: BTC/ETH/SOL: deepest books, keep them even though v1 lost. | T7: coinbase 19994 bars 2024-07-02 to 2026-10-14 | U7: No - stays in cash | V7: 3 | W7: No entries Sat/Sun | X7: bar size + 15 min
A8: A074 | B8: RETRAIN | C8: 2 - next | D8: US stocks | E8: Large US stocks: mean reversion | F8: XOM | G8: 1h | H8: zscore_reversion.none.atr_bracket | I8: -0.7 | J8: 20 | K8: 0 | L8: 0.5 | M8: REJECT | N8: ibs_reversion.trend200.time | O8: rsi2_reversion.trend200.time | P8: zscore_reversion.none.atr_bracket | Q8: Long only. Flat by 3:55 pm ET. Max 5 bars per trade (never overnight). | R8: IBKR Canada (API). Alpaca live not open to Canadians | S8: 2 years of 1h data. Retrain with the new candidate list. | T8: yahoo 3476 bars 2024-10-15 to 2026-10-13 | U8: No - stays in cash | V8: 2 | W8: n/a (market closed) | X8: bar size + 15 min
A9: A075 | B9: RETRAIN | C9: 2 - next | D9: US stocks | E9: Large US stocks: mean reversion | F9: BRK-B | G9: 1h | H9: rsi2_reversion.none.time | I9: -1.9 | J9: 36 | K9: 0 | L9: 0.19 | M9: REJECT | N9: ibs_reversion.trend200.time | O9: rsi2_reversion.trend200.time | P9: zscore_reversion.none.atr_bracket | Q9: Long only. Flat by 3:55 pm ET. Max 5 bars per trade (never overnight). | R9: IBKR Canada (API). Alpaca live not open to Canadians | S9: 2 years of 1h data. Retrain with the new candidate list. | T9: yahoo 3476 bars 2024-10-15 to 2026-10-13 | U9: No - stays in cash | V9: 2 | W9: n/a (market closed) | X9: bar size + 15 min
A10: A076 | B10: RETRAIN | C10: 2 - next | D10: US stocks | E10: Large US stocks: mean reversion | F10: LLY | G10: 1h | H10: zscore_reversion.none.atr_bracket | J10: 0 | K10: 0 | L10: 0.26 | M10: REJECT | N10: ibs_reversion.trend200.time | O10: rsi2_reversion.trend200.time | P10: zscore_reversion.none.atr_bracket | Q10: Long only. Flat by 3:55 pm ET. Max 5 bars per trade (never overnight). | R10: IBKR Canada (API). Alpaca live not open to Canadians | S10: 2 years of 1h data. Retrain with the new candidate list. | T10: yahoo 3476 bars 2024-10-15 to 2026-10-13 | U10: No - stays in cash | V10: 2 | W10: n/a (market closed) | X10: bar size + 15 min
A11: A077 | B11: RETRAIN | C11: 2 - next | D11: US stocks | E11: Large US stocks: mean reversion | F11: V | G11: 1h | H11: rsi2_reversion.none.time | I11: -1.48 | J11: 44 | K11: 0 | L11: 0.4 | M11: REJECT | N11: ibs_reversion.trend200.time | O11: rsi2_reversion.trend200.time | P11: zscore_reversion.none.atr_bracket | Q11: Long only. Flat by 3:55 pm ET. Max 5 bars per trade (never overnight). | R11: IBKR Canada (API). Alpaca live not open to Canadians | S11: 2 years of 1h data. Retrain with the new candidate list. | T11: yahoo 3476 bars 2024-10-15 to 2026-10-13 | U11: No - stays in cash | V11: 2 | W11: n/a (market closed) | X11: bar size + 15 min
A12: A078 | B12: RETRAIN | C12: 2 - next | D12: US stocks | E12: Large US stocks: mean reversion | F12: MA | G12: 1h | H12: zscore_reversion.none.atr_bracket | I12: 0.1 | J12: 8 | K12: 0 | L12: 0.25 | M12: REJECT | N12: ibs_reversion.trend200.time | O12: rsi2_reversion.trend200.time | P12: zscore_reversion.none.atr_bracket | Q12: Long only. Flat by 3:55 pm ET. Max 5 bars per trade (never overnight). | R12: IBKR Canada (API). Alpaca live not open to Canadians | S12: 2 years of 1h data. Retrain with the new candidate list. | T12: yahoo 3476 bars 2024-10-15 to 2026-10-13 | U12: No - stays in cash | V12: 2 | W12: n/a (market closed) | X12: bar size + 15 min
A13: A079 | B13: RETRAIN | C13: 2 - next | D13: US stocks | E13: Large US stocks: mean reversion | F13: UNH | G13: 1h | H13: rsi2_reversion.none.time | I13: -0.81 | J13: 42 | K13: 0 | L13: 0.59 | M13: REJECT | N13: ibs_reversion.trend200.time | O13: rsi2_reversion.trend200.time | P13: zscore_reversion.none.atr_bracket | Q13: Long only. Flat by 3:55 pm ET. Max 5 bars per trade (never overnight). | R13: IBKR Canada (API). Alpaca live not open to Canadians | S13: 2 years of 1h data. Retrain with the new candidate list. | T13: yahoo 3476 bars 2024-10-15 to 2026-10-13 | U13: No - stays in cash | V13: 2 | W13: n/a (market closed) | X13: bar size + 15 min
A14: A080 | B14: RETRAIN | C14: 2 - next | D14: US stocks | E14: Large US stocks: mean reversion | F14: COST | G14: 1h | H14: zscore_reversion.none.atr_bracket | I14: -1.22 | J14: 26 | K14: 0 | L14: 0.06 | M14: REJECT | N14: ibs_reversion.trend200.time | O14: rsi2_reversion.trend200.time | P14: zscore_reversion.none.atr_bracket | Q14: Long only. Flat by 3:55 pm ET. Max 5 bars per trade (never overnight). | R14: IBKR Canada (API). Alpaca live not open to Canadians | S14: 2 years of 1h data. Retrain with the new candidate list. | T14: yahoo 3477 bars 2024-10-15 to 2026-10-13 | U14: No - stays in cash | V14: 2 | W14: n/a (market closed) | X14: bar size + 15 min
A15: A082 | B15: RETRAIN | C15: 2 - next | D15: US stocks | E15: Large US stocks: mean reversion | F15: HD | G15: 1h | H15: zscore_reversion.none.atr_bracket | I15: -2.1 | J15: 24 | K15: 0 | L15: 0.54 | M15: REJECT | N15: ibs_reversion.trend200.time | O15: rsi2_reversion.trend200.time | P15: zscore_reversion.none.atr_bracket | Q15: Long only. Flat by 3:55 pm ET. Max 5 bars per trade (never overnight). | R15: IBKR Canada (API). Alpaca live not open to Canadians | S15: 2 years of 1h data. Retrain with the new candidate list. | T15: yahoo 3476 bars 2024-10-15 to 2026-10-13 | U15: No - stays in cash | V15: 2 | W15: n/a (market closed) | X15: bar size + 15 min
A16: A083 | B16: RETRAIN | C16: 2 - next | D16: US stocks | E16: Large US stocks: mean reversion | F16: PG | G16: 1h | H16: rsi2_reversion.none.time | I16: 1.15 | J16: 25 | K16: 0.01 | L16: 0.11 | M16: REJECT | N16: ibs_reversion.trend200.time | O16: rsi2_reversion.trend200.time | P16: zscore_reversion.none.atr_bracket | Q16: Long only. Flat by 3:55 pm ET. Max 5 bars per trade (never overnight). | R16: IBKR Canada (API). Alpaca live not open to Canadians | S16: 2 years of 1h data. Retrain with the new candidate list. | T16: yahoo 3476 bars 2024-10-15 to 2026-10-13 | U16: No - stays in cash | V16: 2 | W16: n/a (market closed) | X16: bar size + 15 min
A17: A084 | B17: RETRAIN | C17: 2 - next | D17: US stocks | E17: Large US stocks: mean reversion | F17: JNJ | G17: 1h | H17: zscore_reversion.none.atr_bracket | I17: -0.52 | J17: 30 | K17: 0 | L17: 0.5 | M17: REJECT | N17: ibs_reversion.trend200.time | O17: rsi2_reversion.trend200.time | P17: zscore_reversion.none.atr_bracket | Q17: Long only. Flat by 3:55 pm ET. Max 5 bars per trade (never overnight). | R17: IBKR Canada (API). Alpaca live not open to Canadians | S17: 2 years of 1h data. Retrain with the new candidate list. | T17: yahoo 3476 bars 2024-10-15 to 2026-10-13 | U17: No - stays in cash | V17: 2 | W17: n/a (market closed) | X17: bar size + 15 min
A18: A085 | B18: RETRAIN | C18: 2 - next | D18: US stocks | E18: Large US stocks: mean reversion | F18: KO | G18: 1h | H18: zscore_reversion.none.atr_bracket | I18: -1.89 | J18: 14 | K18: 0 | L18: 0.86 | M18: REJECT | N18: ibs_reversion.trend200.time | O18: rsi2_reversion.trend200.time | P18: zscore_reversion.none.atr_bracket | Q18: Long only. Flat by 3:55 pm ET. Max 5 bars per trade (never overnight). | R18: IBKR Canada (API). Alpaca live not open to Canadians | S18: 2 years of 1h data. Retrain with the new candidate list. | T18: yahoo 3476 bars 2024-10-15 to 2026-10-13 | U18: No - stays in cash | V18: 2 | W18: n/a (market closed) | X18: bar size + 15 min
A19: A086 | B19: RETRAIN | C19: 2 - next | D19: US stocks | E19: Large US stocks: mean reversion | F19: PEP | G19: 1h | H19: zscore_reversion.none.atr_bracket | I19: -2.7 | J19: 29 | K19: 0 | L19: 0.86 | M19: REJECT | N19: ibs_reversion.trend200.time | O19: rsi2_reversion.trend200.time | P19: zscore_reversion.none.atr_bracket | Q19: Long only. Flat by 3:55 pm ET. Max 5 bars per trade (never overnight). | R19: IBKR Canada (API). Alpaca live not open to Canadians | S19: 2 years of 1h data. Retrain with the new candidate list. | T19: yahoo 3477 bars 2024-10-15 to 2026-10-13 | U19: No - stays in cash | V19: 2 | W19: n/a (market closed) | X19: bar size + 15 min
A20: A088 | B20: RETRAIN | C20: 2 - next | D20: US stocks | E20: Large US stocks: mean reversion | F20: CVX | G20: 1h | H20: rsi2_reversion.none.time | I20: 0.07 | J20: 29 | K20: 0 | L20: 0.02 | M20: REJECT | N20: ibs_reversion.trend200.time | O20: rsi2_reversion.trend200.time | P20: zscore_reversion.none.atr_bracket | Q20: Long only. Flat by 3:55 pm ET. Max 5 bars per trade (never overnight). | R20: IBKR Canada (API). Alpaca live not open to Canadians | S20: 2 years of 1h data. Retrain with the new candidate list. | T20: yahoo 3476 bars 2024-10-15 to 2026-10-13 | U20: No - stays in cash | V20: 2 | W20: n/a (market closed) | X20: bar size + 15 min
A21: A089 | B21: RETRAIN | C21: 2 - next | D21: US stocks | E21: Large US stocks: mean reversion | F21: BAC | G21: 1h | H21: rsi2_reversion.none.time | I21: -1.26 | J21: 22 | K21: 0 | L21: 0.05 | M21: REJECT | N21: ibs_reversion.trend200.time | O21: rsi2_reversion.trend200.time | P21: zscore_reversion.none.atr_bracket | Q21: Long only. Flat by 3:55 pm ET. Max 5 bars per trade (never overnight). | R21: IBKR Canada (API). Alpaca live not open to Canadians | S21: 2 years of 1h data. Retrain with the new candidate list. | T21: yahoo 3476 bars 2024-10-15 to 2026-10-13 | U21: No - stays in cash | V21: 2 | W21: n/a (market closed) | X21: bar size + 15 min
A22: A004 | B22: RETRAIN | C22: 3 - then | D22: Crypto | E22: Liquid crypto: trend | F22: ZEC-USD | G22: 1h | H22: donchian_breakout.none.trail | I22: 1.39 | J22: 46 | K22: 0.23 | M22: REJECT | N22: donchian_trend.adx.trail | O22: squeeze_breakout.adx.trail | P22: nr7_breakout.relvol.atr_bracket | Q22: Long only. Max 12 bars (12 h) per trade. Max 2 crypto bots open at once. | R22: Verify the coin is on NDAX/Kraken/Coinbase Canada | S22: Not broken in v1 and enough trades. Retrain with new list. | T22: coinbase 19994 bars 2024-07-02 to 2026-10-14 | U22: No - stays in cash | V22: 3 | W22: No entries Sat/Sun | X22: bar size + 15 min
A23: A005 | B23: RETRAIN | C23: 3 - then | D23: Crypto | E23: Liquid crypto: trend | F23: XRP-USD | G23: 1h | H23: donchian_breakout.none.trail | I23: -0.74 | J23: 31 | K23: 0.01 | M23: REJECT | N23: donchian_trend.adx.trail | O23: squeeze_breakout.adx.trail | P23: nr7_breakout.relvol.atr_bracket | Q23: Long only. Max 12 bars (12 h) per trade. Max 2 crypto bots open at once. | R23: Verify the coin is on NDAX/Kraken/Coinbase Canada | S23: Not broken in v1 and enough trades. Retrain with new list. | T23: coinbase 19994 bars 2024-07-02 to 2026-10-14 | U23: No - stays in cash | V23: 3 | W23: No entries Sat/Sun | X23: bar size + 15 min
A24: A006 | B24: RETRAIN | C24: 3 - then | D24: Crypto | E24: Liquid crypto: trend | F24: NEAR-USD | G24: 1h | H24: donchian_breakout.none.trail | I24: -1.24 | J24: 46 | K24: 0 | M24: REJECT | N24: donchian_trend.adx.trail | O24: squeeze_breakout.adx.trail | P24: nr7_breakout.relvol.atr_bracket | Q24: Long only. Max 12 bars (12 h) per trade. Max 2 crypto bots open at once. | R24: Verify the coin is on NDAX/Kraken/Coinbase Canada | S24: Not broken in v1 and enough trades. Retrain with new list. | T24: coinbase 19993 bars 2024-07-02 to 2026-10-14 | U24: No - stays in cash | V24: 3 | W24: No entries Sat/Sun | X24: bar size + 15 min
A25: A015 | B25: RETRAIN | C25: 3 - then | D25: Crypto | E25: Liquid crypto: trend | F25: TAO-USD | G25: 1h | H25: donchian_breakout.none.trail | I25: -1.26 | J25: 23 | K25: 0 | M25: REJECT | N25: donchian_trend.adx.trail | O25: squeeze_breakout.adx.trail | P25: nr7_breakout.relvol.atr_bracket | Q25: Long only. Max 12 bars (12 h) per trade. Max 2 crypto bots open at once. | R25: Verify the coin is on NDAX/Kraken/Coinbase Canada | S25: Not broken in v1 and enough trades. Retrain with new list. | T25: coinbase 14401 bars 2025-02-20 to 2026-10-14 | U25: No - stays in cash | V25: 3 | W25: No entries Sat/Sun | X25: bar size + 15 min
A26: A016 | B26: RETRAIN | C26: 3 - then | D26: Crypto | E26: Liquid crypto: trend | F26: BAT-USD | G26: 1h | H26: donchian_breakout.none.trail | I26: -1.14 | J26: 34 | K26: 0 | M26: REJECT | N26: donchian_trend.adx.trail | O26: squeeze_breakout.adx.trail | P26: nr7_breakout.relvol.atr_bracket | Q26: Long only. Max 12 bars (12 h) per trade. Max 2 crypto bots open at once. | R26: Verify the coin is on NDAX/Kraken/Coinbase Canada | S26: Not broken in v1 and enough trades. Retrain with new list. | T26: coinbase 19985 bars 2024-07-02 to 2026-10-14 | U26: No - stays in cash | V26: 3 | W26: No entries Sat/Sun | X26: bar size + 15 min
A27: A017 | B27: RETRAIN | C27: 3 - then | D27: Crypto | E27: Liquid crypto: trend | F27: XLM-USD | G27: 1h | H27: donchian_breakout.none.trail | I27: -0.6 | J27: 33 | K27: 0 | M27: REJECT | N27: donchian_trend.adx.trail | O27: squeeze_breakout.adx.trail | P27: nr7_breakout.relvol.atr_bracket | Q27: Long only. Max 12 bars (12 h) per trade. Max 2 crypto bots open at once. | R27: Verify the coin is on NDAX/Kraken/Coinbase Canada | S27: Not broken in v1 and enough trades. Retrain with new list. | T27: coinbase 19994 bars 2024-07-02 to 2026-10-14 | U27: No - stays in cash | V27: 3 | W27: No entries Sat/Sun | X27: bar size + 15 min
A28: A020 | B28: RETRAIN | C28: 3 - then | D28: Crypto | E28: Liquid crypto: trend | F28: ONDO-USD | G28: 1h | H28: donchian_breakout.none.trail | I28: -1.47 | J28: 35 | K28: 0 | M28: REJECT | N28: donchian_trend.adx.trail | O28: squeeze_breakout.adx.trail | P28: nr7_breakout.relvol.atr_bracket | Q28: Long only. Max 12 bars (12 h) per trade. Max 2 crypto bots open at once. | R28: Verify the coin is on NDAX/Kraken/Coinbase Canada | S28: Not broken in v1 and enough trades. Retrain with new list. | T28: coinbase 19994 bars 2024-07-02 to 2026-10-14 | U28: No - stays in cash | V28: 3 | W28: No entries Sat/Sun | X28: bar size + 15 min
A29: A021 | B29: RETRAIN | C29: 3 - then | D29: Crypto | E29: Liquid crypto: trend | F29: ENA-USD | G29: 1h | H29: ema_cross.adx.flip | I29: 0.31 | J29: 56 | K29: 0 | L29: 0.52 | M29: REJECT | N29: donchian_trend.adx.trail | O29: squeeze_breakout.adx.trail | P29: nr7_breakout.relvol.atr_bracket | Q29: Long only. Max 12 bars (12 h) per trade. Max 2 crypto bots open at once. | R29: Verify the coin is on NDAX/Kraken/Coinbase Canada | S29: Not broken in v1 and enough trades. Retrain with new list. | T29: coinbase 11882 bars 2025-06-05 to 2026-10-14 | U29: No - stays in cash | V29: 3 | W29: No entries Sat/Sun | X29: bar size + 15 min
A30: A023 | B30: RETRAIN | C30: 3 - then | D30: Crypto | E30: Liquid crypto: trend | F30: HBAR-USD | G30: 1h | H30: donchian_breakout.none.trail | I30: -0.77 | J30: 24 | K30: 0 | M30: REJECT | N30: donchian_trend.adx.trail | O30: squeeze_breakout.adx.trail | P30: nr7_breakout.relvol.atr_bracket | Q30: Long only. Max 12 bars (12 h) per trade. Max 2 crypto bots open at once. | R30: Verify the coin is on NDAX/Kraken/Coinbase Canada | S30: Not broken in v1 and enough trades. Retrain with new list. | T30: coinbase 19993 bars 2024-07-02 to 2026-10-14 | U30: No - stays in cash | V30: 3 | W30: No entries Sat/Sun | X30: bar size + 15 min
A31: A024 | B31: RETRAIN | C31: 3 - then | D31: Crypto | E31: Liquid crypto: trend | F31: USELESS-USD | G31: 1h | H31: ema_cross.adx.flip | I31: 0.3 | J31: 37 | K31: 0 | L31: 0.81 | M31: REJECT | N31: donchian_trend.adx.trail | O31: squeeze_breakout.adx.trail | P31: nr7_breakout.relvol.atr_bracket | Q31: Long only. Max 12 bars (12 h) per trade. Max 2 crypto bots open at once. | R31: Verify the coin is on NDAX/Kraken/Coinbase Canada | S31: Not broken in v1 and enough trades. Retrain with new list. | T31: coinbase 10058 bars 2025-08-20 to 2026-10-14 | U31: No - stays in cash | V31: 3 | W31: No entries Sat/Sun | X31: bar size + 15 min
A32: A025 | B32: RETRAIN | C32: 3 - then | D32: Crypto | E32: Liquid crypto: trend | F32: S-USD | G32: 1h | H32: donchian_breakout.none.trail | I32: 0.73 | J32: 24 | K32: 0.02 | M32: REJECT | N32: donchian_trend.adx.trail | O32: squeeze_breakout.adx.trail | P32: nr7_breakout.relvol.atr_bracket | Q32: Long only. Max 12 bars (12 h) per trade. Max 2 crypto bots open at once. | R32: Verify the coin is on NDAX/Kraken/Coinbase Canada | S32: Not broken in v1 and enough trades. Retrain with new list. | T32: coinbase 11426 bars 2025-06-24 to 2026-10-14 | U32: No - stays in cash | V32: 3 | W32: No entries Sat/Sun | X32: bar size + 15 min
A33: A032 | B33: RETRAIN | C33: 3 - then | D33: Crypto | E33: Liquid crypto: mean reversion | F33: AMP-USD | G33: 1h | H33: bollinger_reversion.adx.time | I33: 0.25 | J33: 30 | K33: 0 | L33: 0.25 | M33: REJECT | N33: rsi2_reversion.trend200.time | O33: connors_rsi_rev.vol_band.time | P33: bollinger_reversion.vol_band.atr_bracket | Q33: Long only. Max 12 bars (12 h) per trade. Max 2 crypto bots open at once. | R33: Verify the coin is on NDAX/Kraken/Coinbase Canada | S33: Not broken in v1 and enough trades. Retrain with new list. | T33: coinbase 19853 bars 2024-07-02 to 2026-10-14 | U33: No - stays in cash | V33: 3 | W33: No entries Sat/Sun | X33: bar size + 15 min
A34: A056 | B34: NEEDS DATA | C34: 4 - blocked (data) | D34: US stocks | E34: Large US stocks: breakouts | F34: AAPL | G34: 15m | H34: orb.relvol.time | I34: 0.69 | J34: 2 | K34: 0.01 | M34: REJECT | N34: orb.relvol.atr_bracket | O34: active_orb.relvol.time | P34: initial_balance_breakout.relvol.atr_bracket | Q34: Long only. Flat by 3:55 pm ET. Max 20 bars per trade (never overnight). | R34: IBKR Canada (API). Alpaca live not open to Canadians | S34: Only 1,067 bars (~2 months) and 0-9 test trades. Result is noise. Get 6+ months of 15m data, then retrain. | T34: yahoo 1067 bars 2026-08-17 to 2026-10-13 | U34: No - stays in cash | V34: 2 | W34: n/a (market closed) | X34: bar size + 5 min
A35: A057 | B35: NEEDS DATA | C35: 4 - blocked (data) | D35: US stocks | E35: Large US stocks: breakouts | F35: MSFT | G35: 15m | H35: vol_breakout.none.atr_bracket | I35: -7.53 | J35: 6 | K35: 0 | M35: REJECT | N35: orb.relvol.atr_bracket | O35: active_orb.relvol.time | P35: initial_balance_breakout.relvol.atr_bracket | Q35: Long only. Flat by 3:55 pm ET. Max 20 bars per trade (never overnight). | R35: IBKR Canada (API). Alpaca live not open to Canadians | S35: Only 1,067 bars (~2 months) and 0-9 test trades. Result is noise. Get 6+ months of 15m data, then retrain. | T35: yahoo 1067 bars 2026-08-17 to 2026-10-13 | U35: No - stays in cash | V35: 2 | W35: n/a (market closed) | X35: bar size + 5 min
A36: A058 | B36: NEEDS DATA | C36: 4 - blocked (data) | D36: US stocks | E36: Large US stocks: breakouts | F36: NVDA | G36: 15m | H36: orb.relvol.time | I36: -7.12 | J36: 3 | K36: 0 | M36: REJECT | N36: orb.relvol.atr_bracket | O36: active_orb.relvol.time | P36: initial_balance_breakout.relvol.atr_bracket | Q36: Long only. Flat by 3:55 pm ET. Max 20 bars per trade (never overnight). | R36: IBKR Canada (API). Alpaca live not open to Canadians | S36: Only 1,067 bars (~2 months) and 0-9 test trades. Result is noise. Get 6+ months of 15m data, then retrain. | T36: yahoo 1067 bars 2026-08-17 to 2026-10-13 | U36: No - stays in cash | V36: 2 | W36: n/a (market closed) | X36: bar size + 5 min
A37: A059 | B37: NEEDS DATA | C37: 4 - blocked (data) | D37: US stocks | E37: Large US stocks: breakouts | F37: AMZN | G37: 15m | H37: orb.relvol.time | I37: 5.94 | J37: 5 | K37: 0.06 | M37: REJECT | N37: orb.relvol.atr_bracket | O37: active_orb.relvol.time | P37: initial_balance_breakout.relvol.atr_bracket | Q37: Long only. Flat by 3:55 pm ET. Max 20 bars per trade (never overnight). | R37: IBKR Canada (API). Alpaca live not open to Canadians | S37: Only 1,067 bars (~2 months) and 0-9 test trades. Result is noise. Get 6+ months of 15m data, then retrain. | T37: yahoo 1067 bars 2026-08-17 to 2026-10-13 | U37: No - stays in cash | V37: 2 | W37: n/a (market closed) | X37: bar size + 5 min
A38: A060 | B38: NEEDS DATA | C38: 4 - blocked (data) | D38: US stocks | E38: Large US stocks: breakouts | F38: TSLA | G38: 15m | H38: orb.relvol.time | I38: -7.32 | J38: 3 | K38: 0 | M38: REJECT | N38: orb.relvol.atr_bracket | O38: active_orb.relvol.time | P38: initial_balance_breakout.relvol.atr_bracket | Q38: Long only. Flat by 3:55 pm ET. Max 20 bars per trade (never overnight). | R38: IBKR Canada (API). Alpaca live not open to Canadians | S38: Only 1,067 bars (~2 months) and 0-9 test trades. Result is noise. Get 6+ months of 15m data, then retrain. | T38: yahoo 1067 bars 2026-08-17 to 2026-10-13 | U38: No - stays in cash | V38: 2 | W38: n/a (market closed) | X38: bar size + 5 min
A39: A062 | B39: NEEDS DATA | C39: 4 - blocked (data) | D39: US stocks | E39: Large US stocks: breakouts | F39: GOOGL | G39: 15m | H39: orb.relvol.time | I39: -4.98 | J39: 3 | K39: 0 | M39: REJECT | N39: orb.relvol.atr_bracket | O39: active_orb.relvol.time | P39: initial_balance_breakout.relvol.atr_bracket | Q39: Long only. Flat by 3:55 pm ET. Max 20 bars per trade (never overnight). | R39: IBKR Canada (API). Alpaca live not open to Canadians | S39: Only 1,067 bars (~2 months) and 0-9 test trades. Result is noise. Get 6+ months of 15m data, then retrain. | T39: yahoo 1067 bars 2026-08-17 to 2026-10-13 | U39: No - stays in cash | V39: 2 | W39: n/a (market closed) | X39: bar size + 5 min
A40: A063 | B40: NEEDS DATA | C40: 4 - blocked (data) | D40: US stocks | E40: Large US stocks: breakouts | F40: AMD | G40: 15m | H40: orb.relvol.time | I40: -3.26 | J40: 4 | K40: 0 | M40: REJECT | N40: orb.relvol.atr_bracket | O40: active_orb.relvol.time | P40: initial_balance_breakout.relvol.atr_bracket | Q40: Long only. Flat by 3:55 pm ET. Max 20 bars per trade (never overnight). | R40: IBKR Canada (API). Alpaca live not open to Canadians | S40: Only 1,067 bars (~2 months) and 0-9 test trades. Result is noise. Get 6+ months of 15m data, then retrain. | T40: yahoo 1067 bars 2026-08-17 to 2026-10-13 | U40: No - stays in cash | V40: 2 | W40: n/a (market closed) | X40: bar size + 5 min
A41: A064 | B41: NEEDS DATA | C41: 4 - blocked (data) | D41: US stocks | E41: Large US stocks: breakouts | F41: NFLX | G41: 15m | H41: orb.relvol.time | I41: 5.58 | J41: 2 | K41: 0.05 | M41: REJECT | N41: orb.relvol.atr_bracket | O41: active_orb.relvol.time | P41: initial_balance_breakout.relvol.atr_bracket | Q41: Long only. Flat by 3:55 pm ET. Max 20 bars per trade (never overnight). | R41: IBKR Canada (API). Alpaca live not open to Canadians | S41: Only 1,067 bars (~2 months) and 0-9 test trades. Result is noise. Get 6+ months of 15m data, then retrain. | T41: yahoo 1067 bars 2026-08-17 to 2026-10-13 | U41: No - stays in cash | V41: 2 | W41: n/a (market closed) | X41: bar size + 5 min
A42: A065 | B42: NEEDS DATA | C42: 4 - blocked (data) | D42: US stocks | E42: Large US stocks: breakouts | F42: AVGO | G42: 15m | H42: vol_breakout.none.atr_bracket | I42: 9.06 | J42: 5 | K42: 0.11 | M42: REJECT | N42: orb.relvol.atr_bracket | O42: active_orb.relvol.time | P42: initial_balance_breakout.relvol.atr_bracket | Q42: Long only. Flat by 3:55 pm ET. Max 20 bars per trade (never overnight). | R42: IBKR Canada (API). Alpaca live not open to Canadians | S42: Only 1,067 bars (~2 months) and 0-9 test trades. Result is noise. Get 6+ months of 15m data, then retrain. | T42: yahoo 1067 bars 2026-08-17 to 2026-10-13 | U42: No - stays in cash | V42: 2 | W42: n/a (market closed) | X42: bar size + 5 min
A43: A066 | B43: NEEDS DATA | C43: 4 - blocked (data) | D43: US stocks | E43: Large US stocks: breakouts | F43: PLTR | G43: 15m | H43: vol_breakout.none.atr_bracket | I43: -6.3 | J43: 4 | K43: 0 | M43: REJECT | N43: orb.relvol.atr_bracket | O43: active_orb.relvol.time | P43: initial_balance_breakout.relvol.atr_bracket | Q43: Long only. Flat by 3:55 pm ET. Max 20 bars per trade (never overnight). | R43: IBKR Canada (API). Alpaca live not open to Canadians | S43: Only 1,067 bars (~2 months) and 0-9 test trades. Result is noise. Get 6+ months of 15m data, then retrain. | T43: yahoo 1067 bars 2026-08-17 to 2026-10-13 | U43: No - stays in cash | V43: 2 | W43: n/a (market closed) | X43: bar size + 5 min
A44: A067 | B44: NEEDS DATA | C44: 4 - blocked (data) | D44: US stocks | E44: Large US stocks: breakouts | F44: COIN | G44: 15m | H44: vol_breakout.none.atr_bracket | I44: -11.08 | J44: 5 | K44: 0 | M44: REJECT | N44: orb.relvol.atr_bracket | O44: active_orb.relvol.time | P44: initial_balance_breakout.relvol.atr_bracket | Q44: Long only. Flat by 3:55 pm ET. Max 20 bars per trade (never overnight). | R44: IBKR Canada (API). Alpaca live not open to Canadians | S44: Only 1,067 bars (~2 months) and 0-9 test trades. Result is noise. Get 6+ months of 15m data, then retrain. | T44: yahoo 1067 bars 2026-08-17 to 2026-10-13 | U44: No - stays in cash | V44: 2 | W44: n/a (market closed) | X44: bar size + 5 min
A45: A068 | B45: NEEDS DATA | C45: 4 - blocked (data) | D45: US stocks | E45: Large US stocks: breakouts | F45: UBER | G45: 15m | H45: orb.relvol.time | I45: 4.22 | J45: 2 | K45: 0.02 | M45: REJECT | N45: orb.relvol.atr_bracket | O45: active_orb.relvol.time | P45: initial_balance_breakout.relvol.atr_bracket | Q45: Long only. Flat by 3:55 pm ET. Max 20 bars per trade (never overnight). | R45: IBKR Canada (API). Alpaca live not open to Canadians | S45: Only 1,067 bars (~2 months) and 0-9 test trades. Result is noise. Get 6+ months of 15m data, then retrain. | T45: yahoo 1067 bars 2026-08-17 to 2026-10-13 | U45: No - stays in cash | V45: 2 | W45: n/a (market closed) | X45: bar size + 5 min
... A65: A045 | B65: MEME SHADOW | C65: 5 - paper sleeve (max 5%) | D65: Meme coins | E65: Meme coins: trend sleeve | F65: BONK-USD | G65: 1h | H65: donchian_breakout.none.trail | I65: -1.57 | J65: 28 | K65: 0 | M65: REJECT | N65: donchian_trend.adx.trail | O65: vol_breakout.adx.atr_bracket | P65: squeeze_breakout.adx.trail | Q65: Long only. Max 12 bars. Meme sleeve: max 5% of paper capital, risk 0.25% per trade, hard stop. | R65: NDAX asset statement found | S65: Kept as a paper-only sleeve (you asked for memes). Old results were the worst, so it must pass the same gate. Mean-reversion dropped for memes (they leave ranges fast); trend candidates only. | T65: coinbase 19994 bars 2024-07-02 to 2026-10-14 | U65: No - stays in cash | V65: 4 | W65: No entries Sat/Sun (untested) | X65: bar size + 15 min
A66: A046 | B66: MEME SHADOW | C66: 5 - paper sleeve (max 5%) | D66: Meme coins | E66: Meme coins: trend sleeve | F66: FARTCOIN-USD | G66: 1h | H66: tsmom.none.trail | I66: -3.28 | J66: 22 | K66: 0 | L66: 0.02 | M66: REJECT | N66: donchian_trend.adx.trail | O66: vol_breakout.adx.atr_bracket | P66: squeeze_breakout.adx.trail | Q66: Long only. Max 12 bars. Meme sleeve: max 5% of paper capital, risk 0.25% per trade, hard stop. | R66: Not confirmed on NDAX/Kraken Canada - verify before any use | S66: Kept as a paper-only sleeve (you asked for memes). Old results were the worst, so it must pass the same gate. Mean-reversion dropped for memes (they leave ranges fast); trend candidates only. | T66: coinbase 11714 bars 2025-06-12 to 2026-10-14 | U66: No - stays in cash | V66: 4 | W66: No entries Sat/Sun (untested) | X66: bar size + 15 min
A67: A047 | B67: MEME SHADOW | C67: 5 - paper sleeve (max 5%) | D67: Meme coins | E67: Meme coins: trend sleeve | F67: GIGA-USD | G67: 1h | H67: donchian_breakout.none.trail | I67: -3.33 | J67: 22 | K67: 0 | M67: REJECT | N67: donchian_trend.adx.trail | O67: vol_breakout.adx.atr_bracket | P67: squeeze_breakout.adx.trail | Q67: Long only. Max 12 bars. Meme sleeve: max 5% of paper capital, risk 0.25% per trade, hard stop. | R67: Not confirmed on NDAX/Kraken Canada - verify before any use | S67: Kept as a paper-only sleeve (you asked for memes). Old results were the worst, so it must pass the same gate. Mean-reversion dropped for memes (they leave ranges fast); trend candidates only. | T67: coinbase 15797 bars 2024-12-11 to 2026-10-14 | U67: No - stays in cash | V67: 4 | W67: No entries Sat/Sun (untested) | X67: bar size + 15 min
A68: A048 | B68: MEME SHADOW | C68: 5 - paper sleeve (max 5%) | D68: Meme coins | E68: Meme coins: trend sleeve | F68: SHIB-USD | G68: 1h | H68: tsmom.none.trail | I68: -1.74 | J68: 78 | K68: 0 | L68: 0.05 | M68: REJECT | N68: donchian_trend.adx.trail | O68: vol_breakout.adx.atr_bracket | P68: squeeze_breakout.adx.trail | Q68: Long only. Max 12 bars. Meme sleeve: max 5% of paper capital, risk 0.25% per trade, hard stop. | R68: NDAX asset statement found | S68: Kept as a paper-only sleeve (you asked for memes). Old results were the worst, so it must pass the same gate. Mean-reversion dropped for memes (they leave ranges fast); trend candidates only. | T68: coinbase 19994 bars 2024-07-02 to 2026-10-14 | U68: No - stays in cash | V68: 4 | W68: No entries Sat/Sun (untested) | X68: bar size + 15 min
A69: A049 | B69: MEME SHADOW | C69: 5 - paper sleeve (max 5%) | D69: Meme coins | E69: Meme coins: trend sleeve | F69: SPX-USD | G69: 1h | H69: zscore_reversion.none.atr_bracket | I69: -1.33 | J69: 11 | K69: 0 | L69: 0 | M69: REJECT | N69: donchian_trend.adx.trail | O69: vol_breakout.adx.atr_bracket | P69: squeeze_breakout.adx.trail | Q69: Long only. Max 12 bars. Meme sleeve: max 5% of paper capital, risk 0.25% per trade, hard stop. | R69: Not confirmed on NDAX/Kraken Canada - verify before any use | S69: Kept as a paper-only sleeve (you asked for memes). Old results were the worst, so it must pass the same gate. Mean-reversion dropped for memes (they leave ranges fast); trend candidates only. | T69: coinbase 9576 bars 2025-09-09 to 2026-10-14 | U69: No - stays in cash | V69: 4 | W69: No entries Sat/Sun (untested) | X69: bar size + 15 min
A70: A050 | B70: MEME SHADOW | C70: 5 - paper sleeve (max 5%) | D70: Meme coins | E70: Meme coins: trend sleeve | F70: WIF-USD | G70: 1h | H70: zscore_reversion.none.atr_bracket | I70: -3.84 | J70: 17 | K70: 0 | L70: 0 | M70: REJECT | N70: donchian_trend.adx.trail | O70: vol_breakout.adx.atr_bracket | P70: squeeze_breakout.adx.trail | Q70: Long only. Max 12 bars. Meme sleeve: max 5% of paper capital, risk 0.25% per trade, hard stop. | R70: NDAX asset statement found | S70: Kept as a paper-only sleeve (you asked for memes). Old results were the worst, so it must pass the same gate. Mean-reversion dropped for memes (they leave ranges fast); trend candidates only. | T70: coinbase 16714 bars 2024-11-13 to 2026-10-14 | U70: No - stays in cash | V70: 4 | W70: No entries Sat/Sun (untested) | X70: bar size + 15 min
A71: A051 | B71: MEME SHADOW | C71: 5 - paper sleeve (max 5%) | D71: Meme coins | E71: Meme coins: trend sleeve | F71: FLOKI-USD | G71: 1h | H71: zscore_reversion.none.atr_bracket | I71: -3.37 | J71: 20 | K71: 0 | L71: 0 | M71: REJECT | N71: donchian_trend.adx.trail | O71: vol_breakout.adx.atr_bracket | P71: squeeze_breakout.adx.trail | Q71: Long only. Max 12 bars. Meme sleeve: max 5% of paper capital, risk 0.25% per trade, hard stop. | R71: Not confirmed on NDAX/Kraken Canada - verify before any use | S71: Kept as a paper-only sleeve (you asked for memes). Old results were the worst, so it must pass the same gate. Mean-reversion dropped for memes (they leave ranges fast); trend candidates only. | T71: coinbase 16355 bars 2024-11-21 to 2026-10-14 | U71: No - stays in cash | V71: 4 | W71: No entries Sat/Sun (untested) | X71: bar size + 15 min
A72: A052 | B72: MEME SHADOW | C72: 5 - paper sleeve (max 5%) | D72: Meme coins | E72: Meme coins: trend sleeve | F72: MOODENG-USD | G72: 1h | H72: zscore_reversion.none.atr_bracket | I72: -2.95 | J72: 16 | K72: 0 | L72: 0 | M72: REJECT | N72: donchian_trend.adx.trail | O72: vol_breakout.adx.atr_bracket | P72: squeeze_breakout.adx.trail | Q72: Long only. Max 12 bars. Meme sleeve: max 5% of paper capital, risk 0.25% per trade, hard stop. | R72: Not confirmed on NDAX/Kraken Canada - verify before any use | S72: Kept as a paper-only sleeve (you asked for memes). Old results were the worst, so it must pass the same gate. Mean-reversion dropped for memes (they leave ranges fast); trend candidates only. | T72: coinbase 16263 bars 2024-12-04 to 2026-10-14 | U72: No - stays in cash | V72: 4 | W72: No entries Sat/Sun (untested) | X72: bar size + 15 min
A73: A053 | B73: MEME SHADOW | C73: 5 - paper sleeve (max 5%) | D73: Meme coins | E73: Meme coins: trend sleeve | F73: POPCAT-USD | G73: 1h | H73: zscore_reversion.none.atr_bracket | I73: -4.16 | J73: 18 | K73: 0 | L73: 0.15 | M73: REJECT | N73: donchian_trend.adx.trail | O73: vol_breakout.adx.atr_bracket | P73: squeeze_breakout.adx.trail | Q73: Long only. Max 12 bars. Meme sleeve: max 5% of paper capital, risk 0.25% per trade, hard stop. | R73: Not confirmed on NDAX/Kraken Canada - verify before any use | S73: Kept as a paper-only sleeve (you asked for memes). Old results were the worst, so it must pass the same gate. Mean-reversion dropped for memes (they leave ranges fast); trend candidates only. | T73: coinbase 14510 bars 2025-02-13 to 2026-10-14 | U73: No - stays in cash | V73: 4 | W73: No entries Sat/Sun (untested) | X73: bar size + 15 min
A74: A054 | B74: MEME SHADOW | C74: 5 - paper sleeve (max 5%) | D74: Meme coins | E74: Meme coins: trend sleeve | F74: TURBO-USD | G74: 1h | H74: bollinger_reversion.adx.time | I74: -3.56 | J74: 17 | K74: 0 | L74: 0.02 | M74: REJECT | N74: donchian_trend.adx.trail | O74: vol_breakout.adx.atr_bracket | P74: squeeze_breakout.adx.trail | Q74: Long only. Max 12 bars. Meme sleeve: max 5% of paper capital, risk 0.25% per trade, hard stop. | R74: Not confirmed on NDAX/Kraken Canada - verify before any use | S74: Kept as a paper-only sleeve (you asked for memes). Old results were the worst, so it must pass the same gate. Mean-reversion dropped for memes (they leave ranges fast); trend candidates only. | T74: coinbase 16077 bars 2024-12-11 to 2026-10-14 | U74: No - stays in cash | V74: 4 | W74: No entries Sat/Sun (untested) | X74: bar size + 15 min
A75: A055 | B75: MEME SHADOW | C75: 5 - paper sleeve (max 5%) | D75: Meme coins | E75: Meme coins: trend sleeve | F75: PNUT-USD | G75: 1h | H75: zscore_reversion.none.atr_bracket | I75: -3.06 | J75: 19 | K75: 0 | L75: 0.04 | M75: REJECT | N75: donchian_trend.adx.trail | O75: vol_breakout.adx.atr_bracket | P75: squeeze_breakout.adx.trail | Q75: Long only. Max 12 bars. Meme sleeve: max 5% of paper capital, risk 0.25% per trade, hard stop. | R75: Not confirmed on NDAX/Kraken Canada - verify before any use | S75: Kept as a paper-only sleeve (you asked for memes). Old results were the worst, so it must pass the same gate. Mean-reversion dropped for memes (they leave ranges fast); trend candidates only. | T75: coinbase 14854 bars 2025-01-14 to 2026-10-14 | U75: No - stays in cash | V75: 4 | W75: No entries Sat/Sun (untested) | X75: bar size + 15 min
A76: A007 | B76: PARKED | C76: 5 - off | D76: Crypto | E76: Liquid crypto: trend | F76: QNT-USD | G76: 1h | H76: tsmom.none.trail | I76: -5.59 | J76: 62 | K76: 0 | L76: 0 | M76: REJECT | N76: donchian_trend.adx.trail | O76: squeeze_breakout.adx.trail | P76: nr7_breakout.relvol.atr_bracket | Q76: Long only. Max 12 bars (12 h) per trade. Max 2 crypto bots open at once. | R76: Verify the coin is on NDAX/Kraken/Coinbase Canada | S76: v1 clearly lost (test Sharpe below -1.5) or too few trades to judge. Park, do not delete. | T76: coinbase 19993 bars 2024-07-02 to 2026-10-14 | U76: No - stays in cash | V76: 3 | W76: No entries Sat/Sun | X76: bar size + 15 min
A77: A008 | B77: PARKED | C77: 5 - off | D77: Crypto | E77: Liquid crypto: trend | F77: HYPE-USD | G77: 1h | H77: donchian_breakout.none.trail | I77: -6.41 | J77: 21 | K77: 0 | M77: REJECT | N77: donchian_trend.adx.trail | O77: squeeze_breakout.adx.trail | P77: nr7_breakout.relvol.atr_bracket | Q77: Long only. Max 12 bars (12 h) per trade. Max 2 crypto bots open at once. | R77: Verify the coin is on NDAX/Kraken/Coinbase Canada | S77: v1 clearly lost (test Sharpe below -1.5) or too few trades to judge. Park, do not delete. | T77: coinbase 6004 bars 2026-02-05 to 2026-10-14 | U77: No - stays in cash | V77: 3 | W77: No entries Sat/Sun | X77: bar size + 15 min
A78: A009 | B78: PARKED | C78: 5 - off | D78: Crypto | E78: Liquid crypto: trend | F78: SUI-USD | G78: 1h | H78: donchian_breakout.none.trail | I78: -3.1 | J78: 39 | K78: 0 | M78: REJECT | N78: donchian_trend.adx.trail | O78: squeeze_breakout.adx.trail | P78: nr7_breakout.relvol.atr_bracket | Q78: Long only. Max 12 bars (12 h) per trade. Max 2 crypto bots open at once. | R78: Verify the coin is on NDAX/Kraken/Coinbase Canada | S78: v1 clearly lost (test Sharpe below -1.5) or too few trades to judge. Park, do not delete. | T78: coinbase 19994 bars 2024-07-02 to 2026-10-14 | U78: No - stays in cash | V78: 3 | W78: No entries Sat/Sun | X78: bar size + 15 min
A79: A010 | B79: PARKED | C79: 5 - off | D79: Crypto | E79: Liquid crypto: trend | F79: ADA-USD | G79: 1h | H79: donchian_breakout.none.trail | I79: -2.22 | J79: 32 | K79: 0 | M79: REJECT | N79: donchian_trend.adx.trail | O79: squeeze_breakout.adx.trail | P79: nr7_breakout.relvol.atr_bracket | Q79: Long only. Max 12 bars (12 h) per trade. Max 2 crypto bots open at once. | R79: Verify the coin is on NDAX/Kraken/Coinbase Canada | S79: v1 clearly lost (test Sharpe below -1.5) or too few trades to judge. Park, do not delete. | T79: coinbase 19994 bars 2024-07-02 to 2026-10-14 | U79: No - stays in cash | V79: 3 | W79: No entries Sat/Sun | X79: bar size + 15 min
A80: A011 | B80: PARKED | C80: 5 - off | D80: Crypto | E80: Liquid crypto: trend | F80: INJ-USD | G80: 1h | H80: donchian_breakout.none.trail | I80: -1.99 | J80: 45 | K80: 0 | M80: REJECT | N80: donchian_trend.adx.trail | O80: squeeze_breakout.adx.trail | P80: nr7_breakout.relvol.atr_bracket | Q80: Long only. Max 12 bars (12 h) per trade. Max 2 crypto bots open at once. | R80: Verify the coin is on NDAX/Kraken/Coinbase Canada | S80: v1 clearly lost (test Sharpe below -1.5) or too few trades to judge. Park, do not delete. | T80: coinbase 19994 bars 2024-07-02 to 2026-10-14 | U80: No - stays in cash | V80: 3 | W80: No entries Sat/Sun | X80: bar size + 15 min
A81: A012 | B81: PARKED | C81: 5 - off | D81: Crypto | E81: Liquid crypto: trend | F81: UNI-USD | G81: 1h | H81: tsmom.none.trail | I81: -2.46 | J81: 64 | K81: 0 | L81: 0 | M81: REJECT | N81: donchian_trend.adx.trail | O81: squeeze_breakout.adx.trail | P81: nr7_breakout.relvol.atr_bracket | Q81: Long only. Max 12 bars (12 h) per trade. Max 2 crypto bots open at once. | R81: Verify the coin is on NDAX/Kraken/Coinbase Canada | S81: v1 clearly lost (test Sharpe below -1.5) or too few trades to judge. Park, do not delete. | T81: coinbase 19994 bars 2024-07-02 to 2026-10-14 | U81: No - stays in cash | V81: 3 | W81: No entries Sat/Sun | X81: bar size + 15 min
A82: A013 | B82: PARKED | C82: 5 - off | D82: Crypto | E82: Liquid crypto: trend | F82: STRK-USD | G82: 1h | H82: tsmom.none.trail | I82: -3.47 | J82: 72 | K82: 0 | L82: 0 | M82: REJECT | N82: donchian_trend.adx.trail | O82: squeeze_breakout.adx.trail | P82: nr7_breakout.relvol.atr_bracket | Q82: Long only. Max 12 bars (12 h) per trade. Max 2 crypto bots open at once. | R82: Verify the coin is on NDAX/Kraken/Coinbase Canada | S82: v1 clearly lost (test Sharpe below -1.5) or too few trades to judge. Park, do not delete. | T82: coinbase 19719 bars 2024-07-02 to 2026-10-14 | U82: No - stays in cash | V82: 3 | W82: No entries Sat/Sun | X82: bar size + 15 min
A83: A014 | B83: PARKED | C83: 5 - off | D83: Crypto | E83: Liquid crypto: trend | F83: LINK-USD | G83: 1h | H83: donchian_breakout.none.trail | I83: -2.78 | J83: 40 | K83: 0 | M83: REJECT | N83: donchian_trend.adx.trail | O83: squeeze_breakout.adx.trail | P83: nr7_breakout.relvol.atr_bracket | Q83: Long only. Max 12 bars (12 h) per trade. Max 2 crypto bots open at once. | R83: Verify the coin is on NDAX/Kraken/Coinbase Canada | S83: v1 clearly lost (test Sharpe below -1.5) or too few trades to judge. Park, do not delete. | T83: coinbase 19994 bars 2024-07-02 to 2026-10-14 | U83: No - stays in cash | V83: 3 | W83: No entries Sat/Sun | X83: bar size + 15 min
A84: A018 | B84: PARKED | C84: 5 - off | D84: Crypto | E84: Liquid crypto: trend | F84: VVV-USD | G84: 1h | H84: ema_cross.adx.flip | I84: -3.6 | J84: 65 | K84: 0 | L84: 0.33 | M84: REJECT | N84: donchian_trend.adx.trail | O84: squeeze_breakout.adx.trail | P84: nr7_breakout.relvol.atr_bracket | Q84: Long only. Max 12 bars (12 h) per trade. Max 2 crypto bots open at once. | R84: Verify the coin is on NDAX/Kraken/Coinbase Canada | S84: v1 clearly lost (test Sharpe below -1.5) or too few trades to judge. Park, do not delete. | T84: coinbase 14791 bars 2025-01-28 to 2026-10-14 | U84: No - stays in cash | V84: 3 | W84: No entries Sat/Sun | X84: bar size + 15 min
A85: A019 | B85: PARKED | C85: 5 - off | D85: Crypto | E85: Liquid crypto: trend | F85: LTC-USD | G85: 1h | H85: donchian_breakout.none.trail | I85: -2.94 | J85: 38 | K85: 0 | M85: REJECT | N85: donchian_trend.adx.trail | O85: squeeze_breakout.adx.trail | P85: nr7_breakout.relvol.atr_bracket | Q85: Long only. Max 12 bars (12 h) per trade. Max 2 crypto bots open at once. | R85: Verify the coin is on NDAX/Kraken/Coinbase Canada | S85: v1 clearly lost (test Sharpe below -1.5) or too few trades to judge. Park, do not delete. | T85: coinbase 19994 bars 2024-07-02 to 2026-10-14 | U85: No - stays in cash | V85: 3 | W85: No entries Sat/Sun | X85: bar size + 15 min
A86: A022 | B86: PARKED | C86: 5 - off | D86: Crypto | E86: Liquid crypto: trend | F86: PUMP-USD | G86: 1h | H86: donchian_breakout.none.trail | I86: -1.64 | J86: 29 | K86: 0 | M86: REJECT | N86: donchian_trend.adx.trail | O86: squeeze_breakout.adx.trail | P86: nr7_breakout.relvol.atr_bracket | Q86: Long only. Max 12 bars (12 h) per trade. Max 2 crypto bots open at once. | R86: Verify the coin is on NDAX/Kraken/Coinbase Canada | S86: v1 clearly lost (test Sharpe below -1.5) or too few trades to judge. Park, do not delete. | T86: coinbase 10925 bars 2025-07-15 to 2026-10-14 | U86: No - stays in cash | V86: 3 | W86: No entries Sat/Sun | X86: bar size + 15 min
A87: A026 | B87: PARKED | C87: 5 - off | D87: Crypto | E87: Liquid crypto: mean reversion | F87: RENDER-USD | G87: 1h | H87: bollinger_reversion.adx.time | I87: -2.93 | J87: 26 | K87: 0 | L87: 0 | M87: REJECT | N87: rsi2_reversion.trend200.time | O87: connors_rsi_rev.vol_band.time | P87: bollinger_reversion.vol_band.atr_bracket | Q87: Long only. Max 12 bars (12 h) per trade. Max 2 crypto bots open at once. | R87: Verify the coin is on NDAX/Kraken/Coinbase Canada | S87: v1 clearly lost (test Sharpe below -1.5) or too few trades to judge. Park, do not delete. | T87: coinbase 19994 bars 2024-07-02 to 2026-10-14 | U87: No - stays in cash | V87: 3 | W87: No entries Sat/Sun | X87: bar size + 15 min
A88: A027 | B88: PARKED | C88: 5 - off | D88: Crypto | E88: Liquid crypto: mean reversion | F88: AERO-USD | G88: 1h | H88: zscore_reversion.none.atr_bracket | I88: -4 | J88: 18 | K88: 0 | L88: 0.13 | M88: REJECT | N88: rsi2_reversion.trend200.time | O88: connors_rsi_rev.vol_band.time | P88: bollinger_reversion.vol_band.atr_bracket | Q88: Long only. Max 12 bars (12 h) per trade. Max 2 crypto bots open at once. | R88: Verify the coin is on NDAX/Kraken/Coinbase Canada | S88: v1 clearly lost (test Sharpe below -1.5) or too few trades to judge. Park, do not delete. | T88: coinbase 19994 bars 2024-07-02 to 2026-10-14 | U88: No - stays in cash | V88: 3 | W88: No entries Sat/Sun | X88: bar size + 15 min
A89: A028 | B89: PARKED | C89: 5 - off | D89: Crypto | E89: Liquid crypto: mean reversion | F89: AVAX-USD | G89: 1h | H89: zscore_reversion.none.atr_bracket | I89: -2.91 | J89: 43 | K89: 0 | L89: 0.01 | M89: REJECT | N89: rsi2_reversion.trend200.time | O89: connors_rsi_rev.vol_band.time | P89: bollinger_reversion.vol_band.atr_bracket | Q89: Long only. Max 12 bars (12 h) per trade. Max 2 crypto bots open at once. | R89: Verify the coin is on NDAX/Kraken/Coinbase Canada | S89: v1 clearly lost (test Sharpe below -1.5) or too few trades to judge. Park, do not delete. | T89: coinbase 19994 bars 2024-07-02 to 2026-10-14 | U89: No - stays in cash | V89: 3 | W89: No entries Sat/Sun | X89: bar size + 15 min
A90: A029 | B90: PARKED | C90: 5 - off | D90: Crypto | E90: Liquid crypto: mean reversion | F90: FIL-USD | G90: 1h | H90: zscore_reversion.none.atr_bracket | I90: -3.28 | J90: 15 | K90: 0 | L90: 0 | M90: REJECT | N90: rsi2_reversion.trend200.time | O90: connors_rsi_rev.vol_band.time | P90: bollinger_reversion.vol_band.atr_bracket | Q90: Long only. Max 12 bars (12 h) per trade. Max 2 crypto bots open at once. | R90: Verify the coin is on NDAX/Kraken/Coinbase Canada | S90: v1 clearly lost (test Sharpe below -1.5) or too few trades to judge. Park, do not delete. | T90: coinbase 19993 bars 2024-07-02 to 2026-10-14 | U90: No - stays in cash | V90: 3 | W90: No entries Sat/Sun | X90: bar size + 15 min
A91: A030 | B91: PARKED | C91: 5 - off | D91: Crypto | E91: Liquid crypto: mean reversion | F91: OP-USD | G91: 1h | H91: zscore_reversion.none.atr_bracket | I91: -3.3 | J91: 30 | K91: 0 | L91: 0 | M91: REJECT | N91: rsi2_reversion.trend200.time | O91: connors_rsi_rev.vol_band.time | P91: bollinger_reversion.vol_band.atr_bracket | Q91: Long only. Max 12 bars (12 h) per trade. Max 2 crypto bots open at once. | R91: Verify the coin is on NDAX/Kraken/Coinbase Canada | S91: v1 clearly lost (test Sharpe below -1.5) or too few trades to judge. Park, do not delete. | T91: coinbase 19903 bars 2024-07-02 to 2026-10-14 | U91: No - stays in cash | V91: 3 | W91: No entries Sat/Sun | X91: bar size + 15 min
A92: A031 | B92: PARKED | C92: 5 - off | D92: Crypto | E92: Liquid crypto: mean reversion | F92: FET-USD | G92: 1h | H92: zscore_reversion.none.atr_bracket | I92: -5.1 | J92: 31 | K92: 0 | L92: 0.23 | M92: REJECT | N92: rsi2_reversion.trend200.time | O92: connors_rsi_rev.vol_band.time | P92: bollinger_reversion.vol_band.atr_bracket | Q92: Long only. Max 12 bars (12 h) per trade. Max 2 crypto bots open at once. | R92: Verify the coin is on NDAX/Kraken/Coinbase Canada | S92: v1 clearly lost (test Sharpe below -1.5) or too few trades to judge. Park, do not delete. | T92: coinbase 19993 bars 2024-07-02 to 2026-10-14 | U92: No - stays in cash | V92: 3 | W92: No entries Sat/Sun | X92: bar size + 15 min
A93: A033 | B93: PARKED | C93: 5 - off | D93: Crypto | E93: Liquid crypto: mean reversion | F93: STX-USD | G93: 1h | H93: bollinger_reversion.adx.time | I93: -4.85 | J93: 22 | K93: 0 | L93: 0.02 | M93: REJECT | N93: rsi2_reversion.trend200.time | O93: connors_rsi_rev.vol_band.time | P93: bollinger_reversion.vol_band.atr_bracket | Q93: Long only. Max 12 bars (12 h) per trade. Max 2 crypto bots open at once. | R93: Verify the coin is on NDAX/Kraken/Coinbase Canada | S93: v1 clearly lost (test Sharpe below -1.5) or too few trades to judge. Park, do not delete. | T93: coinbase 19992 bars 2024-07-02 to 2026-10-14 | U93: No - stays in cash | V93: 3 | W93: No entries Sat/Sun | X93: bar size + 15 min
A94: A034 | B94: PARKED | C94: 5 - off | D94: Crypto | E94: Liquid crypto: mean reversion | F94: SD-USD | G94: 1h | H94: zscore_reversion.none.atr_bracket | I94: -4 | J94: 22 | K94: 0 | L94: 0.01 | M94: REJECT | N94: rsi2_reversion.trend200.time | O94: connors_rsi_rev.vol_band.time | P94: bollinger_reversion.vol_band.atr_bracket | Q94: Long only. Max 12 bars (12 h) per trade. Max 2 crypto bots open at once. | R94: Verify the coin is on NDAX/Kraken/Coinbase Canada | S94: v1 clearly lost (test Sharpe below -1.5) or too few trades to judge. Park, do not delete. | T94: coinbase 18247 bars 2024-07-30 to 2026-10-14 | U94: No - stays in cash | V94: 3 | W94: No entries Sat/Sun | X94: bar size + 15 min
A95: A035 | B95: PARKED | C95: 5 - off | D95: Crypto | E95: Liquid crypto: mean reversion | F95: DOT-USD | G95: 1h | H95: zscore_reversion.none.atr_bracket | I95: -5.46 | J95: 31 | K95: 0 | L95: 0 | M95: REJECT | N95: rsi2_reversion.trend200.time | O95: connors_rsi_rev.vol_band.time | P95: bollinger_reversion.vol_band.atr_bracket | Q95: Long only. Max 12 bars (12 h) per trade. Max 2 crypto bots open at once. | R95: Verify the coin is on NDAX/Kraken/Coinbase Canada | S95: v1 clearly lost (test Sharpe below -1.5) or too few trades to judge. Park, do not delete. | T95: coinbase 19994 bars 2024-07-02 to 2026-10-14 | U95: No - stays in cash | V95: 3 | W95: No entries Sat/Sun | X95: bar size + 15 min
A96: A036 | B96: PARKED | C96: 5 - off | D96: Crypto | E96: Liquid crypto: mean reversion | F96: LIGHTER-USD | G96: 1h | H96: zscore_reversion.none.atr_bracket | I96: -4.4 | J96: 2 | K96: 0 | L96: 0.47 | M96: REJECT | N96: rsi2_reversion.trend200.time | O96: connors_rsi_rev.vol_band.time | P96: bollinger_reversion.vol_band.atr_bracket | Q96: Long only. Max 12 bars (12 h) per trade. Max 2 crypto bots open at once. | R96: Verify the coin is on NDAX/Kraken/Coinbase Canada | S96: v1 clearly lost (test Sharpe below -1.5) or too few trades to judge. Park, do not delete. | T96: coinbase 6499 bars 2026-01-15 to 2026-10-14 | U96: No - stays in cash | V96: 3 | W96: No entries Sat/Sun | X96: bar size + 15 min
A97: A037 | B97: PARKED | C97: 5 - off | D97: Crypto | E97: Liquid crypto: mean reversion | F97: ZRO-USD | G97: 1h | H97: zscore_reversion.none.atr_bracket | I97: -3.1 | J97: 15 | K97: 0 | L97: 0.06 | M97: REJECT | N97: rsi2_reversion.trend200.time | O97: connors_rsi_rev.vol_band.time | P97: bollinger_reversion.vol_band.atr_bracket | Q97: Long only. Max 12 bars (12 h) per trade. Max 2 crypto bots open at once. | R97: Verify the coin is on NDAX/Kraken/Coinbase Canada | S97: v1 clearly lost (test Sharpe below -1.5) or too few trades to judge. Park, do not delete. | T97: coinbase 19992 bars 2024-07-02 to 2026-10-14 | U97: No - stays in cash | V97: 3 | W97: No entries Sat/Sun | X97: bar size + 15 min
A98: A038 | B98: PARKED | C98: 5 - off | D98: Crypto | E98: Liquid crypto: mean reversion | F98: MON-USD | G98: 1h | H98: zscore_reversion.none.atr_bracket | I98: -4.48 | J98: 6 | K98: 0 | L98: 0 | M98: REJECT | N98: rsi2_reversion.trend200.time | O98: connors_rsi_rev.vol_band.time | P98: bollinger_reversion.vol_band.atr_bracket | Q98: Long only. Max 12 bars (12 h) per trade. Max 2 crypto bots open at once. | R98: Verify the coin is on NDAX/Kraken/Coinbase Canada | S98: v1 clearly lost (test Sharpe below -1.5) or too few trades to judge. Park, do not delete. | T98: coinbase 7762 bars 2025-11-24 to 2026-10-14 | U98: No - stays in cash | V98: 3 | W98: No entries Sat/Sun | X98: bar size + 15 min
... A100: A040 | B100: PARKED | C100: 5 - off | D100: Crypto | E100: Liquid crypto: mean reversion | F100: ICP-USD | G100: 1h | H100: bollinger_reversion.adx.time | I100: -3.51 | J100: 21 | K100: 0 | L100: 0 | M100: REJECT | N100: rsi2_reversion.trend200.time | O100: connors_rsi_rev.vol_band.time | P100: bollinger_reversion.vol_band.atr_bracket | Q100: Long only. Max 12 bars (12 h) per trade. Max 2 crypto bots open at once. | R100: Verify the coin is on NDAX/Kraken/Coinbase Canada | S100: v1 clearly lost (test Sharpe below -1.5) or too few trades to judge. Park, do not delete. | T100: coinbase 19983 bars 2024-07-02 to 2026-10-14 | U100: No - stays in cash | V100: 3 | W100: No entries Sat/Sun | X100: bar size + 15 min

Sheet Roles
A1: Role | B1: Bar | C1: Bots in role (not parked) | D1: Candidate 1 | E1: Candidate 2 | F1: Candidate 3 | G1: Old test trades (all bots in role, old strategies, indicative only) | H1: Plan | I1: Extra candidate (v5, new)
A2: Large US stocks: mean reversion | B2: 1h | C2: =COUNTIFS(Bots!E:E,A2,Bots!B:B,"<>PARKED") -> 17 | D2: ibs_reversion.trend200.time | E2: rsi2_reversion.trend200.time | F2: zscore_reversion.none.atr_bracket | G2: =SUMIFS(Bots!J:J,Bots!E:E,A2) -> 409 | H2: Pick ONE strategy for the whole role on pooled train/validation. Test once on pooled test. Includes WATCH bots A073/A081/A087.
A3: Large US stocks: intraday momentum | B3: 15m | C3: =COUNTIFS(Bots!E:E,A3,Bots!B:B,"<>PARKED") -> 11 | D3: first_hour_momentum.session.time | E3: active_orb.relvol.atr_bracket | F3: noise_band_momentum.none.time | G3: =SUMIFS(Bots!J:J,Bots!E:E,A3) -> 50 | H3: Blocked until 6+ months of 15m data. Opening-range ideas are cost-sensitive: check the cost rule.
A4: Large US stocks: breakouts | B4: 15m | C4: =COUNTIFS(Bots!E:E,A4,Bots!B:B,"<>PARKED") -> 16 | D4: orb.relvol.atr_bracket | E4: active_orb.relvol.time | F4: initial_balance_breakout.relvol.atr_bracket | G4: =SUMIFS(Bots!J:J,Bots!E:E,A4) -> 55 | H4: Blocked until 6+ months of 15m data. Check cost rule.
A5: Crypto majors: trend | B5: 1h | C5: =COUNTIFS(Bots!E:E,A5,Bots!B:B,"<>PARKED") -> 3 | D5: donchian_trend.adx.trail | E5: vol_breakout.adx.atr_bracket | F5: nr7_breakout.adx.atr_bracket | G5: =SUMIFS(Bots!J:J,Bots!E:E,A5) -> 192 | H5: BTC, ETH, SOL: deepest books. Check real exchange fees first. | I5: vol_gate_swing.btc.long_only (NEW, 96h swing - build first)
A6: Liquid crypto: trend | B6: 1h | C6: =COUNTIFS(Bots!E:E,A6,Bots!B:B,"<>PARKED") -> 11 | D6: donchian_trend.adx.trail | E6: squeeze_breakout.adx.trail | F6: nr7_breakout.relvol.atr_bracket | G6: =SUMIFS(Bots!J:J,Bots!E:E,A6) -> 896 | H6: Pool with majors if the first test is thin. Check real exchange fees.
A7: Liquid crypto: mean reversion | B7: 1h | C7: =COUNTIFS(Bots!E:E,A7,Bots!B:B,"<>PARKED") -> 1 | D7: rsi2_reversion.trend200.time | E7: connors_rsi_rev.vol_band.time | F7: bollinger_reversion.vol_band.atr_bracket | G7: =SUMIFS(Bots!J:J,Bots!E:E,A7) -> 337 | H7: Only AMP is active. Park the role if the pooled test cannot reach 30 trades.
A8: Meme coins: trend sleeve | B8: 1h | C8: =COUNTIFS(Bots!E:E,A8,Bots!B:B,"<>PARKED") -> 15 | D8: donchian_trend.adx.trail | E8: vol_breakout.adx.atr_bracket | F8: squeeze_breakout.adx.trail | G8: =SUMIFS(Bots!J:J,Bots!E:E,A8) -> 381 | H8: All 15 meme bots, one test. Paper-only, max 5% of paper capital. Expect it to fail the gate; that is a fine answer.
A9: Total tries (all candidates) | C9: =COUNTA(D2:F8)+COUNTA(I2:I8) -> 22
A10: Rule of thumb: about 45 tries max on 5 years of daily data (Bailey et al.). Now 22. Add the 4 VWAP tries and the crypto session-ORB try only after the first round, and count them.

Sheet Next steps
A1: Order | B1: What | C1: Action | D1: Pass condition / note
A2: 1 | B2: Build the safety layer first | C2: Risk engine with hard limits, kill switch, stale-data halt, duplicate-order check. The starter kit (policy.py) is a tested first draft: have it reviewed, then simulate failures (cut the feed, send bad prices, restart mid-trade). Jarvus must not be able to change it. | D2: Do before any signal work. See JARVUS_RISK_CHECKLIST.md.
A3: 2 | B3: Get a real data feed | C3: Years of 1-60 min bars for US stocks, dated and split-adjusted, including delisted names. Stop relying on yfinance. | D3: Needed for the 15m bots and for any live decision.
A4: 3 | B4: Run the quality gate as a program | C4: quality_gate.py in the kit computes trade count, Deflated Sharpe, 2x-cost profit, walk-forward folds and a sign-flip test. PBO, the random-direction placebo and buy-and-hold need bar data, so the gate stays CLOSED until you supply them. | D4: Gate verdicts come from code, never from Jarvus.
A5: 4 | B5: Retrain WATCH bots A073, A081, A087 + stock MR role | C5: Role-level test with forced-flat day-trade settings, long only, next-bar fills, costs on. | D5: Pooled test trades 30+, DSR 0.95+, beats buy-and-hold and the random-direction control.
A6: 5 | B6: Crypto majors: build the volatility gate, then test hold times | C6: Build vol_gate.overlay, then vol_gate_swing.btc.long_only. Test 12h, 24h and 96h limits with 3-4 ATR stops and your REAL fees. Apply the cost rule: over 20% of 1R = half size, over 33% = WAIT. | D6: Same gate. Expect the 12h day-trade version to be the hardest.
A7: 6 | B7: Stocks-in-play ORB research track | C7: Build ONE pooled strategy on minute data and a big universe (see strategy file, New sheet). It cannot run as one bot per stock. | D7: Same gate. Best-documented stock idea, but authors sell education: treat results as an upper bound.
A8: 7 | B8: Unblock the 15m bots | C8: Only after 6+ months of 15m data. Opening-range ideas are cost-sensitive. | D8: Same gate.
A9: 8 | B9: Build the 4 VWAP variants and the crypto session ORB | C9: Then add them as a second round. Count them in the DSR. | D9: Do not trade untested code.
A10: 9 | B10: Shadow log | C10: Every bot logs signals with no money. Compare shadow results to the backtest. A big gap means the backtest lied. | D10: Needed before any trust.
A11: 10 | B11: Voice Jarvis, read-only | C11: Start with Claude voice mode + the daily report call. Add the voice command router and read-only tools from the kit after the shadow log works. Voice never gets keys or order powers. | D11: See JARVUS_4_VOICE_AND_LAPTOP_GUIDE.md.
A12: 11 | B12: Weekly review | C12: Promote only on a full pass on unseen data. Demote on fresh-data failure. Re-check all after any model or data change. | D12: Keep the roster small.

Sheet Fleet feed
A1: Field | B1: Type | C1: Meaning | D1: Rule
A2: bot_id | B2: text | C2: Bot id, for example A073
A3: symbol | B3: text | C3: What it trades
A4: role | B4: text | C4: Role from the Roles sheet
A5: status | B5: text | C5: WATCH / RETRAIN / NEEDS DATA / MEME SHADOW / PARKED, plus ACTIVE-PAPER once passed
A6: verdict | B6: text | C6: REJECT / RESEARCH FURTHER / PAPER TEST (from the gate, never from Jarvus)
A7: last_bar_time | B7: UTC time | C7: Time of the last CLOSED bar the bot used | D7: Stale if older than the Bots column X rule
A8: last_signal | B8: text | C8: LONG / NONE (long only)
A9: open_position | B9: yes/no + size, entry, stop | C9: Paper position, if any | D9: Unknown position = pause the bot
A10: pnl_today_usd, pnl_week_usd | B10: number | C10: Paper profit/loss
A11: trades_today, win_rate, avg_r | B11: numbers | C11: Daily record
A12: cost_r_avg | B12: number | C12: Average cost in R on the bot's trades | D12: Over 0.20 = warning; over 0.33 = pause
A13: slippage_vs_model | B13: ratio | C13: Real slippage divided by the model's slippage | D13: Over 2.0 = pause
A14: max_drawdown_pct, backtest_max_dd_pct | B14: numbers | C14: Bot drawdown vs its backtest maximum | D14: Over 1.5x backtest = pause
A15: days_since_last_trade | B15: number | C15: Silent bots are flagged | D15: Over 10 days = flag in weekly report
A16: error | B16: text or empty | C16: Any error the bot raised | D16: Any error = pause
A17: heartbeat_time | B17: UTC time | C17: Bot says 'I am alive' every cycle | D17: Missing for 2 cycles = pause
A18: correlation_id | B18: text | C18: One id per decision; ties input, decision and result in the audit log | D18: Required

Sheet Auto-pause rules
A1: Rule | B1: Trigger | C1: Action | D1: Who enforces it
A2: Slippage | B2: Real slippage over 2x the model | C2: Pause that bot | D2: Risk engine (code)
A3: Drawdown | B3: Bot drawdown over 1.5x its backtest maximum | C3: Pause | D3: Risk engine (code)
A4: Live-paper Sharpe | B4: Below 0 over the last 50 trades | C4: Demote to shadow | D4: Gate / auditor (code)
A5: Losing streak | B5: 3 losses in a row on one bot | C5: Pause for the day | D5: Risk engine (code)
A6: Fleet day loss | B6: -3% of paper capital | C6: HALT everything | D6: Risk engine (code)
A7: Fleet week loss | B7: -6% of paper capital | C7: HALT everything and ask Abhi for a review | D7: Risk engine (code)
A8: Crypto + meme risk | B8: Combined open risk over 40% of fleet risk | C8: Pause new entries in crypto and meme | D8: Risk engine (code)
A9: Meme sleeve | B9: Over 5% of paper capital | C9: Pause new meme entries | D9: Risk engine (code)
A10: Cost in R | B10: Bot's average cost over 0.33R | C10: Pause; between 0.20 and 0.33 = half size | D10: Risk engine (code)
A11: Stale data | B11: Last closed bar older than the bot's limit, or two sources disagree | C11: Pause the affected bots | D11: Data service + risk engine
A12: Unknown position / error | B12: Position not matching the log, or a bot error | C12: Pause the affected bots | D12: Risk engine (code)
... A14: HALT file exists | B14: File named HALT is present | C14: Nothing trades until Abhi deletes it at the keyboard | D14: Everything
